{
    "api_url": "https://www.exchangerate-api.com",
    "api_docs": "https://www.exchangerate-api.com/docs/free",
    "api_terms": "https://www.exchangerate-api.com/terms",
    "base": "CDF",
    "date": "2021-04-30",
    "time_last_updated": 1619740801,
    "rates": {
        "CDF": 1,
        "AED": 0.001853,
        "AFN": 0.039479,
        "ALL": 0.051354,
        "AMD": 0.261895,
        "ANG": 0.000903,
        "AOA": 0.32931,
        "ARS": 0.046929,
        "AUD": 0.000649,
        "AWG": 0.000903,
        "AZN": 0.000855,
        "BAM": 0.000813,
        "BBD": 0.001009,
        "BDT": 0.042684,
        "BGN": 0.000813,
        "BHD": 0.00019,
        "BIF": 0.981501,
        "BMD": 0.000504,
        "BND": 0.000668,
        "BOB": 0.003476,
        "BRL": 0.002702,
        "BSD": 0.000504,
        "BTN": 0.037418,
        "BWP": 0.005471,
        "BYN": 0.001289,
        "BZD": 0.001009,
        "CAD": 0.000619,
        "CHF": 0.000459,
        "CLP": 0.351572,
        "CNY": 0.003264,
        "COP": 1.872549,
        "CRC": 0.31062,
        "CUC": 0.000504,
        "CUP": 0.012989,
        "CVE": 0.045861,
        "CZK": 0.010784,
        "DJF": 0.08965,
        "DKK": 0.003103,
        "DOP": 0.028593,
        "DZD": 0.067124,
        "EGP": 0.007889,
        "ERN": 0.007567,
        "ETB": 0.021199,
        "EUR": 0.000416,
        "FJD": 0.001022,
        "FKP": 0.000361,
        "FOK": 0.003103,
        "GBP": 0.000361,
        "GEL": 0.001737,
        "GGP": 0.000361,
        "GHS": 0.002907,
        "GIP": 0.000361,
        "GMD": 0.026164,
        "GNF": 4.986945,
        "GTQ": 0.003884,
        "GYD": 0.105315,
        "HKD": 0.003918,
        "HNL": 0.012096,
        "HRK": 0.003134,
        "HTG": 0.043409,
        "HUF": 0.150553,
        "IDR": 7.263781,
        "ILS": 0.001644,
        "IMP": 0.000361,
        "INR": 0.037418,
        "IQD": 0.734333,
        "IRR": 21.222222,
        "ISK": 0.061779,
        "JMD": 0.077642,
        "JOD": 0.000358,
        "JPY": 0.054982,
        "KES": 0.054291,
        "KGS": 0.042729,
        "KHR": 2.053763,
        "KID": 0.000649,
        "KMF": 0.204617,
        "KRW": 0.559321,
        "KWD": 0.000151,
        "KYD": 0.00042,
        "KZT": 0.216284,
        "LAK": 4.739454,
        "LBP": 0.760449,
        "LKR": 0.09816,
        "LRD": 0.086818,
        "LSL": 0.007202,
        "LYD": 0.002255,
        "MAD": 0.004481,
        "MDL": 0.008955,
        "MGA": 1.904287,
        "MKD": 0.025625,
        "MMK": 0.784072,
        "MNT": 1.435011,
        "MOP": 0.004035,
        "MRU": 0.018139,
        "MUR": 0.020276,
        "MVR": 0.007783,
        "MWK": 0.396924,
        "MXN": 0.010104,
        "MYR": 0.002069,
        "MZN": 0.028465,
        "NAD": 0.007202,
        "NGN": 0.191806,
        "NIO": 0.017587,
        "NOK": 0.004136,
        "NPR": 0.059869,
        "NZD": 0.000696,
        "OMR": 0.000194,
        "PAB": 0.000504,
        "PEN": 0.001933,
        "PGK": 0.00179,
        "PHP": 0.024405,
        "PKR": 0.077328,
        "PLN": 0.00191,
        "PYG": 3.270548,
        "QAR": 0.001836,
        "RON": 0.002048,
        "RSD": 0.048974,
        "RUB": 0.037533,
        "RWF": 0.503825,
        "SAR": 0.001892,
        "SBD": 0.004105,
        "SCR": 0.007122,
        "SDG": 0.191,
        "SEK": 0.004219,
        "SGD": 0.000668,
        "SHP": 0.000361,
        "SLL": 5.148248,
        "SOS": 0.291203,
        "SRD": 0.007124,
        "SSP": 0.089537,
        "STN": 0.01019,
        "SYP": 1.273333,
        "SZL": 0.007202,
        "THB": 0.015768,
        "TJS": 0.005741,
        "TMT": 0.001759,
        "TND": 0.00138,
        "TOP": 0.00114,
        "TRY": 0.004144,
        "TTD": 0.003424,
        "TVD": 0.000649,
        "TWD": 0.014054,
        "TZS": 1.167482,
        "UAH": 0.013987,
        "UGX": 1.813865,
        "USD": 0.000504,
        "UYU": 0.022184,
        "UZS": 5.305556,
        "VES": 1354.609929,
        "VND": 11.601774,
        "VUV": 0.054094,
        "WST": 0.001265,
        "XAF": 0.272822,
        "XCD": 0.001362,
        "XDR": 0.000351,
        "XOF": 0.272822,
        "XPF": 0.049632,
        "YER": 0.126944,
        "ZAR": 0.007202,
        "ZMW": 0.011216
    }
}