{
    "api_url": "https://www.exchangerate-api.com",
    "api_docs": "https://www.exchangerate-api.com/docs/free",
    "api_terms": "https://www.exchangerate-api.com/terms",
    "base": "HUF",
    "date": "2021-04-30",
    "time_last_updated": 1619740801,
    "rates": {
        "HUF": 1,
        "AED": 0.012305,
        "AFN": 0.261742,
        "ALL": 0.341103,
        "AMD": 1.751,
        "ANG": 0.005998,
        "AOA": 2.181341,
        "ARS": 0.313685,
        "AUD": 0.004297,
        "AWG": 0.005998,
        "AZN": 0.005712,
        "BAM": 0.005404,
        "BBD": 0.006701,
        "BDT": 0.284672,
        "BGN": 0.005411,
        "BHD": 0.00126,
        "BIF": 6.529706,
        "BMD": 0.003351,
        "BND": 0.004443,
        "BOB": 0.023081,
        "BRL": 0.017997,
        "BSD": 0.003351,
        "BTN": 0.247972,
        "BWP": 0.036314,
        "BYN": 0.008602,
        "BZD": 0.006701,
        "CAD": 0.00412,
        "CDF": 6.642789,
        "CHF": 0.003049,
        "CLP": 2.338961,
        "CNY": 0.021667,
        "COP": 12.384676,
        "CRC": 2.060887,
        "CUC": 0.003351,
        "CUP": 0.086278,
        "CVE": 0.304665,
        "CZK": 0.07163,
        "DJF": 0.595474,
        "DKK": 0.020613,
        "DOP": 0.190673,
        "DZD": 0.44886,
        "EGP": 0.05256,
        "ERN": 0.050259,
        "ETB": 0.140818,
        "EUR": 0.002763,
        "FJD": 0.006735,
        "FKP": 0.002404,
        "FOK": 0.020613,
        "GBP": 0.002404,
        "GEL": 0.011588,
        "GGP": 0.002404,
        "GHS": 0.019384,
        "GIP": 0.002404,
        "GMD": 0.173804,
        "GNF": 33.127226,
        "GTQ": 0.025828,
        "GYD": 0.710707,
        "HKD": 0.025993,
        "HNL": 0.080719,
        "HRK": 0.020818,
        "HTG": 0.286281,
        "IDR": 48.279056,
        "ILS": 0.010924,
        "IMP": 0.002404,
        "INR": 0.248006,
        "IQD": 4.878019,
        "IRR": 140.702833,
        "ISK": 0.411407,
        "JMD": 0.509383,
        "JOD": 0.002376,
        "JPY": 0.36503,
        "KES": 0.361956,
        "KGS": 0.285179,
        "KHR": 13.642718,
        "KID": 0.004297,
        "KMF": 1.359322,
        "KRW": 3.708172,
        "KWD": 0.001004,
        "KYD": 0.002792,
        "KZT": 1.438294,
        "LAK": 31.665099,
        "LBP": 5.051049,
        "LKR": 0.654633,
        "LRD": 0.57845,
        "LSL": 0.047801,
        "LYD": 0.01498,
        "MAD": 0.029848,
        "MDL": 0.059902,
        "MGA": 12.775062,
        "MKD": 0.170752,
        "MMK": 4.871045,
        "MNT": 9.532478,
        "MOP": 0.02677,
        "MRU": 0.120491,
        "MUR": 0.135357,
        "MVR": 0.051735,
        "MWK": 2.665193,
        "MXN": 0.067115,
        "MYR": 0.013702,
        "MZN": 0.192926,
        "NAD": 0.047801,
        "NGN": 1.329035,
        "NIO": 0.118313,
        "NOK": 0.027519,
        "NPR": 0.396755,
        "NZD": 0.004612,
        "OMR": 0.001288,
        "PAB": 0.003351,
        "PEN": 0.012645,
        "PGK": 0.011798,
        "PHP": 0.161574,
        "PKR": 0.515475,
        "PLN": 0.012651,
        "PYG": 21.582998,
        "QAR": 0.012196,
        "RON": 0.013646,
        "RSD": 0.326163,
        "RUB": 0.249697,
        "RWF": 3.359386,
        "SAR": 0.012565,
        "SBD": 0.026284,
        "SCR": 0.04791,
        "SDG": 1.268773,
        "SEK": 0.027992,
        "SGD": 0.004443,
        "SHP": 0.002404,
        "SLL": 34.198727,
        "SOS": 1.9344,
        "SRD": 0.047325,
        "SSP": 0.597206,
        "STN": 0.067694,
        "SYP": 4.247014,
        "SZL": 0.047801,
        "THB": 0.104678,
        "TJS": 0.03804,
        "TMT": 0.011771,
        "TND": 0.009172,
        "TOP": 0.00748,
        "TRY": 0.027609,
        "TTD": 0.02282,
        "TVD": 0.004297,
        "TWD": 0.09339,
        "TZS": 7.780683,
        "UAH": 0.093104,
        "UGX": 12.011545,
        "USD": 0.003351,
        "UYU": 0.14704,
        "UZS": 35.02,
        "VES": 9134.176154,
        "VND": 77.536486,
        "VUV": 0.356439,
        "WST": 0.00829,
        "XAF": 1.812429,
        "XCD": 0.009047,
        "XDR": 0.002337,
        "XOF": 1.812429,
        "XPF": 0.329718,
        "YER": 0.840869,
        "ZAR": 0.047806,
        "ZMW": 0.074902
    }
}