{
    "api_url": "https://www.exchangerate-api.com",
    "api_docs": "https://www.exchangerate-api.com/docs/free",
    "api_terms": "https://www.exchangerate-api.com/terms",
    "base": "MYR",
    "date": "2021-04-27",
    "time_last_updated": 1619481601,
    "rates": {
        "MYR": 1,
        "AED": 0.895882,
        "AFN": 19.0625,
        "ALL": 24.862441,
        "AMD": 126.963072,
        "ANG": 0.436659,
        "AOA": 159.662798,
        "ARS": 22.718194,
        "AUD": 0.313603,
        "AWG": 0.436659,
        "AZN": 0.414895,
        "BAM": 0.394672,
        "BBD": 0.487887,
        "BDT": 20.712739,
        "BGN": 0.394751,
        "BHD": 0.091723,
        "BIF": 475.464192,
        "BMD": 0.243943,
        "BND": 0.32362,
        "BOB": 1.675901,
        "BRL": 1.332606,
        "BSD": 0.243943,
        "BTN": 18.24195,
        "BWP": 2.632999,
        "BYN": 0.62532,
        "BZD": 0.487887,
        "CAD": 0.303676,
        "CDF": 483.104337,
        "CHF": 0.223348,
        "CLP": 173.927797,
        "CNY": 1.582823,
        "COP": 878.354777,
        "CRC": 149.546889,
        "CUC": 0.243943,
        "CUP": 6.281542,
        "CVE": 22.25065,
        "CZK": 5.233114,
        "DJF": 43.353865,
        "DKK": 1.505449,
        "DOP": 13.830492,
        "DZD": 32.485688,
        "EGP": 3.824293,
        "ERN": 3.659151,
        "ETB": 10.239886,
        "EUR": 0.201793,
        "FJD": 0.496931,
        "FKP": 0.175652,
        "FOK": 1.505449,
        "GBP": 0.175652,
        "GEL": 0.841484,
        "GGP": 0.175652,
        "GHS": 1.406542,
        "GIP": 0.175652,
        "GMD": 12.666599,
        "GNF": 2426.933601,
        "GTQ": 1.878277,
        "GYD": 52.040542,
        "HKD": 1.892954,
        "HNL": 5.849916,
        "HRK": 1.520406,
        "HTG": 20.791173,
        "HUF": 73.784283,
        "IDR": 3524.052594,
        "ILS": 0.797559,
        "IMP": 0.175652,
        "INR": 18.241967,
        "IQD": 355.639116,
        "IRR": 10158.471963,
        "ISK": 30.466492,
        "JMD": 36.897021,
        "JOD": 0.172956,
        "JPY": 26.351051,
        "KES": 26.409841,
        "KGS": 20.678025,
        "KHR": 986.832126,
        "KID": 0.313602,
        "KMF": 99.275403,
        "KRW": 271.48816,
        "KWD": 0.073093,
        "KYD": 0.203286,
        "KZT": 104.868108,
        "LAK": 2297.551789,
        "LBP": 367.744679,
        "LKR": 47.207877,
        "LRD": 42.105263,
        "LSL": 3.481256,
        "LYD": 1.092206,
        "MAD": 2.167729,
        "MDL": 4.3877,
        "MGA": 920.617132,
        "MKD": 12.454315,
        "MMK": 344.143747,
        "MNT": 694.712022,
        "MOP": 1.949738,
        "MRU": 8.764566,
        "MUR": 9.90239,
        "MVR": 3.735552,
        "MWK": 192.811939,
        "MXN": 4.848475,
        "MZN": 13.656093,
        "NAD": 3.481256,
        "NGN": 92.916452,
        "NIO": 8.57645,
        "NOK": 2.025061,
        "NPR": 29.187119,
        "NZD": 0.33792,
        "OMR": 0.093796,
        "PAB": 0.243943,
        "PEN": 0.923896,
        "PGK": 0.854643,
        "PHP": 11.800557,
        "PKR": 37.486852,
        "PLN": 0.922107,
        "PYG": 1576.785378,
        "QAR": 0.887954,
        "RON": 0.993285,
        "RSD": 23.735409,
        "RUB": 18.272113,
        "RWF": 243.705608,
        "SAR": 0.914788,
        "SBD": 1.947697,
        "SCR": 3.397348,
        "SDG": 92.46617,
        "SEK": 2.045392,
        "SGD": 0.323621,
        "SHP": 0.175652,
        "SLL": 2492.349601,
        "SOS": 141.019018,
        "SRD": 3.45023,
        "SSP": 43.31531,
        "STN": 4.943916,
        "SYP": 307.15005,
        "SZL": 3.481256,
        "THB": 7.683934,
        "TJS": 2.758867,
        "TMT": 0.85382,
        "TND": 0.663404,
        "TOP": 0.552623,
        "TRY": 2.030656,
        "TTD": 1.65536,
        "TVD": 0.313602,
        "TWD": 6.823391,
        "TZS": 564.720215,
        "UAH": 6.796291,
        "UGX": 878.02184,
        "USD": 0.243944,
        "UYU": 10.743266,
        "UZS": 2591.083111,
        "VES": 663851.064994,
        "VND": 5622.148542,
        "VUV": 26.51194,
        "WST": 0.613342,
        "XAF": 132.367204,
        "XCD": 0.658647,
        "XDR": 0.169425,
        "XOF": 132.367204,
        "XPF": 24.080303,
        "YER": 61.13756,
        "ZAR": 3.481269,
        "ZMW": 5.420561
    }
}