{
    "provider": "https://www.exchangerate-api.com",
    "WARNING_UPGRADE_TO_V6": "https://www.exchangerate-api.com/docs/free",
    "terms": "https://www.exchangerate-api.com/terms",
    "base": "PEN",
    "date": "2021-05-11",
    "time_last_updated": 1620691201,
    "rates": {
        "PEN": 1,
        "AED": 0.968,
        "AFN": 20.2,
        "ALL": 26.53,
        "AMD": 135.86,
        "ANG": 0.472,
        "AOA": 171.53,
        "ARS": 24.62,
        "AUD": 0.335,
        "AWG": 0.472,
        "AZN": 0.446,
        "BAM": 0.424,
        "BBD": 0.527,
        "BDT": 22.24,
        "BGN": 0.424,
        "BHD": 0.0991,
        "BIF": 515.23,
        "BMD": 0.264,
        "BND": 0.349,
        "BOB": 1.81,
        "BRL": 1.38,
        "BSD": 0.264,
        "BTN": 19.35,
        "BWP": 2.85,
        "BYN": 0.664,
        "BZD": 0.527,
        "CAD": 0.319,
        "CDF": 518.18,
        "CHF": 0.237,
        "CLP": 182.48,
        "CNY": 1.69,
        "COP": 975.02,
        "CRC": 161.49,
        "CUC": 0.264,
        "CUP": 6.79,
        "CVE": 23.9,
        "CZK": 5.53,
        "DJF": 46.86,
        "DKK": 1.62,
        "DOP": 14.85,
        "DZD": 35.06,
        "EGP": 4.12,
        "ERN": 3.95,
        "ETB": 11.09,
        "EUR": 0.217,
        "FJD": 0.535,
        "FKP": 0.187,
        "FOK": 1.62,
        "GBP": 0.187,
        "GEL": 0.897,
        "GGP": 0.187,
        "GHS": 1.5,
        "GIP": 0.187,
        "GMD": 13.55,
        "GNF": 2577.46,
        "GTQ": 2.02,
        "GYD": 54.57,
        "HKD": 2.05,
        "HNL": 6.3,
        "HRK": 1.63,
        "HTG": 22.36,
        "HUF": 77.19,
        "IDR": 3719.49,
        "ILS": 0.853,
        "IMP": 0.187,
        "INR": 19.35,
        "IQD": 380.6,
        "IRR": 10932.97,
        "ISK": 32.53,
        "JMD": 40.05,
        "JOD": 0.187,
        "JPY": 28.67,
        "KES": 27.89,
        "KGS": 22.11,
        "KHR": 1056.16,
        "KID": 0.335,
        "KMF": 106.64,
        "KRW": 293.89,
        "KWD": 0.079,
        "KYD": 0.22,
        "KZT": 111.45,
        "LAK": 2468.05,
        "LBP": 397.46,
        "LKR": 51.7,
        "LRD": 45.14,
        "LSL": 3.7,
        "LYD": 1.17,
        "MAD": 2.32,
        "MDL": 4.67,
        "MGA": 990.94,
        "MKD": 13.4,
        "MMK": 408.53,
        "MNT": 741.91,
        "MOP": 2.11,
        "MRU": 9.39,
        "MUR": 10.66,
        "MVR": 4.03,
        "MWK": 206.58,
        "MXN": 5.25,
        "MYR": 1.08,
        "MZN": 15.01,
        "NAD": 3.7,
        "NGN": 99.85,
        "NIO": 9.1,
        "NOK": 2.17,
        "NPR": 30.97,
        "NZD": 0.362,
        "OMR": 0.101,
        "PAB": 0.264,
        "PGK": 0.921,
        "PHP": 12.57,
        "PKR": 39.77,
        "PLN": 0.984,
        "PYG": 1767.43,
        "QAR": 0.96,
        "RON": 1.06,
        "RSD": 25.37,
        "RUB": 19.51,
        "RWF": 261.06,
        "SAR": 0.989,
        "SBD": 2.1,
        "SCR": 3.92,
        "SDG": 99.49,
        "SEK": 2.19,
        "SGD": 0.349,
        "SHP": 0.187,
        "SLL": 2667.29,
        "SOS": 150.88,
        "SRD": 3.69,
        "SSP": 46.39,
        "STN": 5.31,
        "SYP": 330.11,
        "SZL": 3.7,
        "THB": 8.16,
        "TJS": 2.98,
        "TMT": 0.912,
        "TND": 0.713,
        "TOP": 0.589,
        "TRY": 2.18,
        "TTD": 1.78,
        "TVD": 0.335,
        "TWD": 7.32,
        "TZS": 604.43,
        "UAH": 7.28,
        "UGX": 928.94,
        "USD": 0.264,
        "UYU": 11.53,
        "UZS": 2740.77,
        "VES": 742462.69,
        "VND": 6049.3,
        "VUV": 28.23,
        "WST": 0.66,
        "XAF": 142.19,
        "XCD": 0.712,
        "XDR": 0.183,
        "XOF": 142.19,
        "XPF": 25.87,
        "YER": 65.72,
        "ZAR": 3.7,
        "ZMW": 5.83
    }
}