{
    "api_url": "https://www.exchangerate-api.com",
    "api_docs": "https://www.exchangerate-api.com/docs/free",
    "api_terms": "https://www.exchangerate-api.com/terms",
    "base": "SAR",
    "date": "2021-04-27",
    "time_last_updated": 1619481601,
    "rates": {
        "SAR": 1,
        "AED": 0.979333,
        "AFN": 20.833333,
        "ALL": 27.172067,
        "AMD": 138.789333,
        "ANG": 0.477333,
        "AOA": 174.534944,
        "ARS": 24.8408,
        "AUD": 0.342458,
        "AWG": 0.477333,
        "AZN": 0.453438,
        "BAM": 0.431275,
        "BBD": 0.533333,
        "BDT": 22.637214,
        "BGN": 0.431275,
        "BHD": 0.100267,
        "BIF": 519.752373,
        "BMD": 0.266667,
        "BND": 0.353338,
        "BOB": 1.832918,
        "BRL": 1.457198,
        "BSD": 0.266667,
        "BTN": 19.953321,
        "BWP": 2.885833,
        "BYN": 0.683371,
        "BZD": 0.533333,
        "CAD": 0.330839,
        "CDF": 528.104177,
        "CHF": 0.243967,
        "CLP": 190.214039,
        "CNY": 1.729024,
        "COP": 966.168279,
        "CRC": 163.55855,
        "CUC": 0.266667,
        "CUP": 6.866667,
        "CVE": 24.314245,
        "CZK": 5.710768,
        "DJF": 47.392267,
        "DKK": 1.645069,
        "DOP": 15.184058,
        "DZD": 35.503484,
        "EGP": 4.180711,
        "ERN": 4,
        "ETB": 11.193703,
        "EUR": 0.220514,
        "FJD": 0.541596,
        "FKP": 0.191724,
        "FOK": 1.645069,
        "GBP": 0.191729,
        "GEL": 0.919866,
        "GGP": 0.191724,
        "GHS": 1.538154,
        "GIP": 0.191724,
        "GMD": 13.846457,
        "GNF": 2652.995789,
        "GTQ": 2.05426,
        "GYD": 56.887976,
        "HKD": 2.069566,
        "HNL": 6.393351,
        "HRK": 1.661413,
        "HTG": 22.727813,
        "HUF": 80.443393,
        "IDR": 3856.357627,
        "ILS": 0.867814,
        "IMP": 0.191724,
        "INR": 19.953446,
        "IQD": 388.765921,
        "IRR": 11192.475514,
        "ISK": 33.315279,
        "JMD": 40.639739,
        "JOD": 0.189067,
        "JPY": 28.815384,
        "KES": 28.833177,
        "KGS": 22.604126,
        "KHR": 1078.752823,
        "KID": 0.342451,
        "KMF": 108.482512,
        "KRW": 296.644352,
        "KWD": 0.079901,
        "KYD": 0.222222,
        "KZT": 114.696055,
        "LAK": 2510.985562,
        "LBP": 402,
        "LKR": 51.611668,
        "LRD": 46.016681,
        "LSL": 3.803476,
        "LYD": 1.193942,
        "MAD": 2.370766,
        "MDL": 4.788294,
        "MGA": 1006.370085,
        "MKD": 13.6144,
        "MMK": 376.119114,
        "MNT": 759.422536,
        "MOP": 2.131643,
        "MRU": 9.580961,
        "MUR": 10.758049,
        "MVR": 4.080521,
        "MWK": 210.77184,
        "MXN": 5.294937,
        "MYR": 1.09315,
        "MZN": 14.928121,
        "NAD": 3.803476,
        "NGN": 106.128764,
        "NIO": 9.373169,
        "NOK": 2.212871,
        "NPR": 31.925314,
        "NZD": 0.369209,
        "OMR": 0.102533,
        "PAB": 0.266667,
        "PEN": 1.013223,
        "PGK": 0.93405,
        "PHP": 12.899303,
        "PKR": 40.9993,
        "PLN": 1.006881,
        "PYG": 1724.521079,
        "QAR": 0.970667,
        "RON": 1.08581,
        "RSD": 25.940337,
        "RUB": 19.96718,
        "RWF": 266.406125,
        "SBD": 2.126245,
        "SCR": 3.713005,
        "SDG": 101.07914,
        "SEK": 2.23668,
        "SGD": 0.35334,
        "SHP": 0.191724,
        "SLL": 2724.505109,
        "SOS": 154.154552,
        "SRD": 3.77161,
        "SSP": 47.350012,
        "STN": 5.40243,
        "SYP": 336.917159,
        "SZL": 3.803476,
        "THB": 8.387949,
        "TJS": 3.015848,
        "TMT": 0.933351,
        "TND": 0.728814,
        "TOP": 0.603277,
        "TRY": 2.215265,
        "TTD": 1.810983,
        "TVD": 0.342451,
        "TWD": 7.432886,
        "TZS": 617.322377,
        "UAH": 7.432006,
        "UGX": 959.807197,
        "USD": 0.266667,
        "UYU": 11.749809,
        "UZS": 2832.435374,
        "VES": 725686.965333,
        "VND": 6144.520065,
        "VUV": 28.94204,
        "WST": 0.669567,
        "XAF": 144.64335,
        "XCD": 0.72,
        "XDR": 0.185526,
        "XOF": 144.64335,
        "XPF": 26.313585,
        "YER": 66.817005,
        "ZAR": 3.803487,
        "ZMW": 5.9261
    }
}