{
    "provider": "https://www.exchangerate-api.com",
    "WARNING_UPGRADE_TO_V6": "https://www.exchangerate-api.com/docs/free",
    "terms": "https://www.exchangerate-api.com/terms",
    "base": "UAH",
    "date": "2021-05-11",
    "time_last_updated": 1620691201,
    "rates": {
        "UAH": 1,
        "AED": 0.132,
        "AFN": 2.77,
        "ALL": 3.64,
        "AMD": 18.81,
        "ANG": 0.0645,
        "AOA": 23.44,
        "ARS": 3.38,
        "AUD": 0.0458,
        "AWG": 0.0645,
        "AZN": 0.0612,
        "BAM": 0.0579,
        "BBD": 0.0721,
        "BDT": 3.05,
        "BGN": 0.0579,
        "BHD": 0.0136,
        "BIF": 70.67,
        "BMD": 0.036,
        "BND": 0.0477,
        "BOB": 0.248,
        "BRL": 0.189,
        "BSD": 0.036,
        "BTN": 2.65,
        "BWP": 0.391,
        "BYN": 0.0912,
        "BZD": 0.0721,
        "CAD": 0.0437,
        "CDF": 71.41,
        "CHF": 0.0324,
        "CLP": 25.05,
        "CNY": 0.231,
        "COP": 133.85,
        "CRC": 22.17,
        "CUC": 0.036,
        "CUP": 0.928,
        "CVE": 3.27,
        "CZK": 0.759,
        "DJF": 6.41,
        "DKK": 0.221,
        "DOP": 2.04,
        "DZD": 4.81,
        "EGP": 0.565,
        "ERN": 0.541,
        "ETB": 1.53,
        "EUR": 0.0296,
        "FJD": 0.0735,
        "FKP": 0.0256,
        "FOK": 0.221,
        "GBP": 0.0256,
        "GEL": 0.123,
        "GGP": 0.0256,
        "GHS": 0.208,
        "GIP": 0.0256,
        "GMD": 1.87,
        "GNF": 355.21,
        "GTQ": 0.278,
        "GYD": 7.69,
        "HKD": 0.28,
        "HNL": 0.865,
        "HRK": 0.223,
        "HTG": 3.13,
        "HUF": 10.6,
        "IDR": 507.84,
        "ILS": 0.117,
        "IMP": 0.0256,
        "INR": 2.65,
        "IQD": 52.45,
        "IRR": 1516.94,
        "ISK": 4.46,
        "JMD": 5.5,
        "JOD": 0.0256,
        "JPY": 3.92,
        "KES": 3.83,
        "KGS": 3.05,
        "KHR": 145.55,
        "KID": 0.0458,
        "KMF": 14.57,
        "KRW": 40.17,
        "KWD": 0.0108,
        "KYD": 0.03,
        "KZT": 15.32,
        "LAK": 338.91,
        "LBP": 54.33,
        "LKR": 7.1,
        "LRD": 6.2,
        "LSL": 0.506,
        "LYD": 0.161,
        "MAD": 0.319,
        "MDL": 0.642,
        "MGA": 135.26,
        "MKD": 1.84,
        "MMK": 56.1,
        "MNT": 102.25,
        "MOP": 0.288,
        "MRU": 1.29,
        "MUR": 1.46,
        "MVR": 0.553,
        "MWK": 28.71,
        "MXN": 0.717,
        "MYR": 0.148,
        "MZN": 2.1,
        "NAD": 0.506,
        "NGN": 13.71,
        "NIO": 1.25,
        "NOK": 0.296,
        "NPR": 4.23,
        "NZD": 0.0494,
        "OMR": 0.0139,
        "PAB": 0.036,
        "PEN": 0.137,
        "PGK": 0.126,
        "PHP": 1.73,
        "PKR": 5.46,
        "PLN": 0.135,
        "PYG": 242.64,
        "QAR": 0.131,
        "RON": 0.146,
        "RSD": 3.48,
        "RUB": 2.66,
        "RWF": 36.02,
        "SAR": 0.135,
        "SBD": 0.288,
        "SCR": 0.538,
        "SDG": 13.71,
        "SEK": 0.3,
        "SGD": 0.0477,
        "SHP": 0.0256,
        "SLL": 367.59,
        "SOS": 20.79,
        "SRD": 0.509,
        "SSP": 6.4,
        "STN": 0.726,
        "SYP": 45.09,
        "SZL": 0.506,
        "THB": 1.12,
        "TJS": 0.407,
        "TMT": 0.126,
        "TND": 0.0979,
        "TOP": 0.0809,
        "TRY": 0.297,
        "TTD": 0.244,
        "TVD": 0.0458,
        "TWD": 1,
        "TZS": 83.45,
        "UGX": 127.96,
        "USD": 0.036,
        "UYU": 1.58,
        "UZS": 376.2,
        "VES": 102231.09,
        "VND": 830.68,
        "VUV": 3.88,
        "WST": 0.0906,
        "XAF": 19.43,
        "XCD": 0.0973,
        "XDR": 0.025,
        "XOF": 19.43,
        "XPF": 3.54,
        "YER": 9.02,
        "ZAR": 0.506,
        "ZMW": 0.806
    }
}